WLO/__init__.py
WLO/src/MessageCreatorAbs.py
WLO/src/WLOWorkerHandler.py
WLO/src/WorkerAbs.py
WLO/src/__init__.py
WLO/src/MessageCreatorWorkers/HelloWorldMessageSample.py
WLO/src/MessageCreatorWorkers/__init__.py
WLO/src/Utils/Utils.py
WLO/src/Utils/__init__.py
WLO/src/Workers/HelloWorldWorkerSample.py
WLO/src/Workers/__init__.py
WLO-0.0.11.data/scripts/ExecutorManager
WLO-0.0.11.dist-info/LICENSE
WLO-0.0.11.dist-info/METADATA
WLO-0.0.11.dist-info/WHEEL
WLO-0.0.11.dist-info/top_level.txt
WLO-0.0.11.dist-info/RECORD
