Metadata-Version: 2.1
Name: WLO
Version: 0.0.11
Summary: This is Workload Optimizer framework - more can be found at the git page
Home-page: https://github.com/idanp/OWL
Author: Idan Perez
Author-email: kimpatz@gmail.com
License: UNKNOWN
Platform: UNKNOWN
Classifier: Programming Language :: Python :: 3
Classifier: License :: OSI Approved :: MIT License
Classifier: Operating System :: OS Independent
Requires-Dist: colorama
